LICENSE
MANIFEST.in
README.md
requirements.txt
setup.py
cert_mailer/__init__.py
cert_mailer/introduce.py
cert_mailer/sendcert.py
cert_mailer.egg-info/PKG-INFO
cert_mailer.egg-info/SOURCES.txt
cert_mailer.egg-info/dependency_links.txt
cert_mailer.egg-info/entry_points.txt
cert_mailer.egg-info/requires.txt
cert_mailer.egg-info/top_level.txt
cert_mailer/helpers/__init__.py
cert_mailer/helpers/mandrill.py
cert_mailer/helpers/sendgrid.py
cert_mailer/helpers/stdout.py
tests/__init__.py
tests/test_cert_mailer.py