Metadata-Version: 1.0
Name: cert-mailer
Version: 0.0.4
Summary: mails blockchain certificates and introductions
Home-page: https://github.com/stuartf/cert-mailer
Author: D. Stuart Freeman
Author-email: stuart.freeman@c21u.gatech.edu
License: MIT
Platform: UNKNOWN
